mcp_python_interpreter/__init__.py
mcp_python_interpreter/main.py
mcp_python_interpreter/server.py
mseep_mcp_python_interpreter-1.1.1.dist-info/licenses/LICENSE
mseep_mcp_python_interpreter-1.1.1.dist-info/METADATA
mseep_mcp_python_interpreter-1.1.1.dist-info/WHEEL
mseep_mcp_python_interpreter-1.1.1.dist-info/top_level.txt
mseep_mcp_python_interpreter-1.1.1.dist-info/RECORD
